{
    "TypeID": 49,
    "ColorID": 0,
    "FightType": 0,
    "ArenaID": 8,
    "EffectID": -1,
    "Gold": 9,
    "UseItem1": 0,
    "UseItem2": 0,
    "UseItem3": 0,
    "UseItem4": 0,
    "HpRecoverFlag": 0,
    "GiftItem": 0,
    "NameLabel": "DP_Trainers_Name_TR_SAILOR_12",
    "MsgFieldPokeOne": "",
    "MsgFieldBefore": "1-SAILOR_08_TRMSG_REVENGE_FIGHT_START",
    "MsgFieldRevenge": "1-SAILOR_08_TRMSG_REVENGE_FIGHT_START",
    "MsgFieldAfter": "1-SAILOR_08_TRMSG_FIGHT_AFTER",
    "MsgBattle": [
        "",
        "",
        "",
        "",
        "",
        "",
        "1-SAILOR_12_TRMSG_FIGHT_LOSE",
        "ee501"
    ],
    "SeqBattle": [],
    "AIBit": 9
}