{
    "TrainerID": 72,
    "LabelTrType": "DP_Trainers_Type_TR_CHAMPION_01",
    "Sex": 1,
    "Group": 5,
    "BallId": 4,
    "FieldEncount": [
        "01",
        "02"
    ],
    "BtlEffId": [
        23,
        72,
        73,
        68
    ],
    "EyeBgm": "EV215",
    "ModelID": "tr0001_00",
    "Hand": 2,
    "HoldBallHand": 0,
    "HelpHand": 2,
    "HelpHoldBallHand": 0,
    "ThrowTime": 0.009999999776482582,
    "CaptureThrowTime": 0.009999999776482582,
    "LoseLoopTime": 4.159999847412109,
    "TrainerEffect": "",
    "Age": 2
}